addict_tracking_changes/__init__.py
addict_tracking_changes/addict.py
addict_tracking_changes/trackedlist.py
addict_tracking_changes-1.0.6.dist-info/LICENSE
addict_tracking_changes-1.0.6.dist-info/WHEEL
addict_tracking_changes-1.0.6.dist-info/METADATA
addict_tracking_changes-1.0.6.dist-info/RECORD
