Metadata-Version: 2.1
Name: addict-tracking-changes
Version: 1.0.6
Summary: Addict dictionary enhanced with ability to track changes -- currently only supports field additions
Maintainer-email: Kabira K <kabira@monallabs.in>
Requires-Python: >=3.11
Requires-Dist: json-fix
Project-URL: Documentation, https://ofjustpy.github.io/addict-tracking-changes/
Project-URL: Home, https://webworks.monallabs.in/ofjustpy/addict-tracking-changes
Project-URL: Source, https://github.com/ofjustpy/addict-tracking-changes
